{
  "lab.subtitle_investigate_environmental_impact": "Investigate the environmental impact of commuting and the benefits of carpooling/public transit.",
  "lab.subtitle_measure_much_metal": "Measure how much metal rods expand when heated, and observe the massive forces generated.",
  "lab.subtitle_investigate_relationship_between": "Investigate the relationship between gas volume and temperature at constant pressure.",
  "lab.subtitle_investigate_different_materials": "Investigate how different materials and thicknesses affect the rate of heat transfer.",
  "lab.subtitle_examine_external_internal": "Examine the external and internal macroscopic structures of a mammalian kidney.",
  "lab.subtitle_investigate_virtual_images": "Investigate virtual images using the parallax pin method with real-world noise.",
  "lab.subtitle_investigate_voltage_current": "Investigate voltage, current, and equivalent resistance in parallel branches.",
  "lab.subtitle_investigate_relationship_between_1": "Investigate the relationship between wave speed, tension, and linear density.",
  "lab.subtitle_determine_refractive_index": "Determine the refractive index by measuring incident and refracted angles.",
  "lab.subtitle_determine_relationship_between": "Determine the relationship between heater power and convection velocity.",
  "lab.subtitle_observe_forces_extensions": "Observe forces and extensions when springs are connected sequentially.",
  "lab.subtitle_investigate_speed_pathways": "Investigate the speed and pathways of a monosynaptic patellar reflex.",
  "lab.subtitle_determine_thermal_conductivity": "Determine the thermal conductivity of materials using Fourier's Law.",
  "lab.subtitle_determine_specific_latent": "Determine specific latent heat using continuous electrical heating.",
  "lab.subtitle_determine_specific_heat": "Determine specific heat capacity by analyzing thermal equilibrium.",
  "lab.subtitle_investigate_speed_mechanical": "Investigate the speed of a mechanical wave through a solid medium.",
  "lab.subtitle_prepare_presentation_based": "Prepare a presentation based on a movie or story about cybercrime",
  "lab.subtitle_excel_functions_calculate": "Use Excel functions to calculate scores for the Pak vs NZ series.",
  "lab.subtitle_analyze_carrier_wave": "Analyze how a carrier wave is modulated by an information signal.",
  "lab.subtitle_investigate_magnetic_field": "Investigate magnetic field lines using compasses and iron filings",
  "lab.subtitle_compare_heating_rates": "Compare heating rates of a matt black can vs a shiny silver can.",
  "lab.subtitle_investigate_electromagnetic_forces": "Investigate the electromagnetic forces that drive a DIY speaker.",
  "lab.subtitle_investigate_induced_when": "Investigate the induced EMF when a magnet moves through a coil.",
  "lab.subtitle_quantitative_analysis_critical": "Quantitative analysis of critical angles and macrobending loss.",
  "lab.subtitle_investigate_relationship_between_2": "Investigate the relationship between liquid depth and pressure.",
  "lab.subtitle_haemodialysis_membranes_extracorporeal": "Haemodialysis Membranes & Extracorporeal Shockwave Lithotripsy",
  "lab.subtitle_install_antivirus_system": "Install an antivirus and run a system scan to remove threats.",
  "lab.subtitle_measure_infrared_radiation": "Measure infrared radiation emitted from 4 different surfaces.",
  "lab.subtitle_practice_filling_secure": "Practice filling out secure online forms on the NR3C portal.",
  "lab.subtitle_determine_real_thermal": "Determine the real thermal expansivity of an unknown liquid.",
  "lab.subtitle_prepare_data_draw": "Prepare data and draw corresponding charts for 3 scenarios.",
  "lab.subtitle_investigate_wave_refraction": "Investigate wave refraction and Snell's Law quantitatively.",
  "lab.subtitle_analyze_current_equivalent": "Analyze current and equivalent resistance in a series loop.",
  "lab.subtitle_investigate_sound_transmission": "Investigate sound transmission in a vacuum using a bell jar",
  "lab.subtitle_visualize_mechanical_vibrations": "Visualize mechanical vibrations of a tuning fork in fluids",
  "lab.subtitle_draft_your_startup": "Draft your startup pitch deck and present it to partners.",
  "lab.subtitle_practice_creating_folders": "Practice creating folders and navigating the file system",
  "lab.subtitle_strike_materials_hear": "Strike materials to hear if they produce a ringing sound",
  "lab.subtitle_quantitative_analysis_ionizing": "Quantitative analysis of ionizing radiation absorption.",
  "lab.subtitle_investigate_bending_light": "Investigate the bending of light across different media",
  "lab.subtitle_observe_closed_environment": "Observe how a closed environment traps thermal energy",
  "lab.subtitle_assemble_components_communication": "Assemble the components of the communication cycle.",
  "lab.subtitle_determine_specific_heat_1": "Determine specific heat using the electrical method",
  "lab.subtitle_investigate_static_kinetic": "Investigate Static, Kinetic, and Rolling Friction",
  "lab.subtitle_household_ingredients_formulate": "Mix household ingredients to formulate toothpaste",
  "lab.subtitle_create_edit_delete": "Create, edit, delete & recover files and folders",
  "lab.subtitle_test_different_solutions": "Test different solutions with universal pH paper",
  "lab.subtitle_materials_with_hammer": "Hit materials with a hammer to test malleability",
  "lab.subtitle_chatelier_principle_process": "Le Chatelier's Principle & Process Optimization",
  "lab.subtitle_identify_devices_configure": "Identify devices and configure the server rack.",
  "lab.subtitle_investigate_snell_critical": "Investigate Snell's Law and the Critical Angle.",
  "lab.subtitle_mass_remains_constant": "Mass remains constant before and after reaction",
  "lab.subtitle_observe_termite_behavior": "Observe termite behavior towards light vs dark",
  "lab.subtitle_determine_specific_charge": "Determine the specific charge of an electron.",
  "lab.subtitle_extract_visible_strands": "Extract visible DNA strands from a strawberry",
  "lab.subtitle_magnetic_fields_generated": "Magnetic fields generated by electric current",
  "lab.subtitle_convert_kinetic_energy": "Convert kinetic energy into electrical energy",
  "lab.subtitle_medical_diagnostics_resuscitation": "Medical Diagnostics & Resuscitation Training",
  "lab.subtitle_observe_color_changes": "Observe color changes, precipitates, and gas",
  "lab.subtitle_antibiotic_mechanisms_ocean": "Antibiotic Mechanisms & Ocean Acidification",
  "lab.subtitle_drop_objects_water": "Drop objects in water to test their density",
  "lab.subtitle_test_materials_bend": "Test if materials bend or break under force",
  "lab.subtitle_count_number_elements": "Count the number of elements in each period",
  "lab.subtitle_parabolic_mirror_concentrating": "Parabolic mirror concentrating solar energy",
  "lab.subtitle_test_different_materials": "Test different materials with litmus paper",
  "lab.subtitle_model_genetic_recombination": "Model genetic recombination during meiosis",
  "lab.subtitle_combine_powders_make": "Combine raw powders to make washing powder",
  "lab.subtitle_observe_heat_travels": "Observe how heat travels through materials",
  "lab.subtitle_enzyme_kinetics_macromolecule": "Enzyme Kinetics & Macromolecule Detection",
  "lab.subtitle_crystallography_conformations": "X-Ray Crystallography & DNA Conformations",
  "lab.subtitle_water_calcium_chloride": "Water + Calcium Chloride (Releases Heat)",
  "lab.subtitle_over_obstacles_using": "See over obstacles using two 45° mirrors",
  "lab.subtitle_peristalsis_emulsification_simulators": "Peristalsis & Emulsification Simulators",
  "lab.subtitle_quality_control_probability": "Quality Control & Probability Simulator",
  "lab.subtitle_test_sodium_hydroxide": "Test Sodium Hydroxide with litmus paper",
  "lab.subtitle_observe_refraction_different": "Observe refraction in different liquids",
  "lab.subtitle_debugging_database_normalization": "OOP Debugging & Database Normalization",
  "lab.subtitle_group_group_outermost": "Group IA vs Group IIA outermost shells",
  "lab.subtitle_observe_bacterial_fermentation": "Observe bacterial fermentation of milk",
  "lab.subtitle_chemical_process_saponification": "The chemical process of saponification",
  "lab.subtitle_pump_build_pressure": "Pump air to build pressure and launch",
  "lab.subtitle_vacuum_distillation_boiling": "Vacuum Distillation & Boiling Points",
  "lab.subtitle_modeling_taxi_fares": "Modeling Taxi Fares using y = mx + c",
  "lab.subtitle_vinegar_baking_soda": "Vinegar + Baking Soda (Absorbs Heat)",
  "lab.subtitle_observe_involuntary_reflex": "Observe an involuntary reflex action",
  "lab.subtitle_visualizing_wind_direction": "Visualizing wind direction and speed",
  "lab.subtitle_arthroplasty_bone_fracture": "Arthroplasty & Bone Fracture Repair",
  "lab.subtitle_design_anti_cyberbullying": "Design an Anti-Cyberbullying Poster",
  "lab.subtitle_sort_traits_their": "Sort traits by their variation type",
  "lab.subtitle_navigate_laser_through": "Navigate the laser through the maze",
  "lab.subtitle_preparation_cell_identification": "Preparation & Cell Identification",
  "lab.subtitle_exchange_boyle_model": "Gas Exchange & Boyle's Law Model",
  "lab.subtitle_measuring_enthalpy_combustion": "Measuring Enthalpy of Combustion",
  "lab.subtitle_social_media_campaign": "Social Media Campaign Simulation",
  "lab.subtitle_vinegar_baking_soda_1": "Vinegar + Baking Soda propulsion",
  "lab.subtitle_blood_types_hemolytic": "Blood Types & Hemolytic Disease",
  "lab.subtitle_recombinant_thermocycling": "Recombinant DNA & Thermocycling",
  "lab.subtitle_fluid_pressure_multiplies": "Fluid pressure multiplies force",
  "lab.subtitle_identification_biomolecules": "Identification of Biomolecules",
  "lab.subtitle_meselson_stahl_hershey": "Meselson-Stahl & Hershey-Chase",
  "lab.subtitle_bias_cloud_computing": "IoT, AI Bias & Cloud Computing",
  "lab.subtitle_synthesizing_methyl_ethanoate": "Synthesizing Methyl Ethanoate",
  "lab.subtitle_measure_human_reaction": "Measure human reaction time",
  "lab.subtitle_titration_naoh_with": "Titration of NaOH with HCl",
  "lab.subtitle_grade_computer_science": "Grade 10 Computer Science",
  "lab.subtitle_concave_mirror_reflection": "Concave Mirror Reflection",
  "lab.subtitle_casein_polymer_extraction": "Casein polymer extraction",
  "lab.subtitle_pushing_nail_into": "Pushing a nail into wood",
  "lab.subtitle_depolymerisation": "Depolymerisation of PET",
  "lab.subtitle_tests_flame_tests": "Gas Tests & Flame Tests",
  "lab.subtitle_html_fundamentals": "HTML & CSS Fundamentals",
  "lab.subtitle_convex_plane_mirrors": "Convex vs Plane Mirrors",
  "lab.subtitle_immunoassay_simulation": "Immunoassay Simulation",
  "lab.subtitle_mathematics_class": "Mathematics Class 11",
  "lab.subtitle_chemistry": "C10 Chemistry"
}